fragpipe_runner/__init__.py
fragpipe_runner/execute.py
fragpipe_runner/manifest.py
fragpipe_runner/workflow.py
fragpipe_runner-0.1.0.dist-info/WHEEL
fragpipe_runner-0.1.0.dist-info/METADATA
fragpipe_runner-0.1.0.dist-info/RECORD
